.gitignore
LICENSE
MANIFEST.in
README.rst
bootstrap.py
buildout.cfg
setup.py
cs/__init__.py
cs.zestreleaser.changelog.egg-info/PKG-INFO
cs.zestreleaser.changelog.egg-info/SOURCES.txt
cs.zestreleaser.changelog.egg-info/dependency_links.txt
cs.zestreleaser.changelog.egg-info/entry_points.txt
cs.zestreleaser.changelog.egg-info/namespace_packages.txt
cs.zestreleaser.changelog.egg-info/not-zip-safe
cs.zestreleaser.changelog.egg-info/requires.txt
cs.zestreleaser.changelog.egg-info/top_level.txt
cs/zestreleaser/__init__.py
cs/zestreleaser/changelog/__init__.py
docs/HISTORY.txt